dfvue/__init__.py
dfvue/__main__.py
dfvue/_version.py
dfvue/dfvmain.py
dfvue/dfvreadcsv.py
dfvue/dfvscatter.py
dfvue/dfvscreen.py
dfvue/dfvtransform.py
dfvue/dfvue.py
dfvue/dfvutils.py
dfvue/ncvwidgets.py
dfvue/tooltip.py
dfvue/images/__init__.py
dfvue/images/dfvue_icon.ico
dfvue/images/dfvue_icon.png
dfvue/images/image2ico.sh
dfvue/themes/__init__.py
dfvue/themes/azure-2.0/.gitignore
dfvue/themes/azure-2.0/Dark screenshot.png
dfvue/themes/azure-2.0/LICENSE
dfvue/themes/azure-2.0/Light screenshot.png
dfvue/themes/azure-2.0/README.md
dfvue/themes/azure-2.0/azure.tcl
dfvue/themes/azure-2.0/example.py
dfvue/themes/azure-2.0/theme/dark.tcl
dfvue/themes/azure-2.0/theme/light.tcl
dfvue/themes/azure-2.0/theme/dark/box-accent.png
dfvue/themes/azure-2.0/theme/dark/box-basic.png
dfvue/themes/azure-2.0/theme/dark/box-hover.png
dfvue/themes/azure-2.0/theme/dark/box-invalid.png
dfvue/themes/azure-2.0/theme/dark/button-hover.png
dfvue/themes/azure-2.0/theme/dark/card.png
dfvue/themes/azure-2.0/theme/dark/check-accent.png
dfvue/themes/azure-2.0/theme/dark/check-basic.png
dfvue/themes/azure-2.0/theme/dark/check-hover.png
dfvue/themes/azure-2.0/theme/dark/check-tri-accent.png
dfvue/themes/azure-2.0/theme/dark/check-tri-basic.png
dfvue/themes/azure-2.0/theme/dark/check-tri-hover.png
dfvue/themes/azure-2.0/theme/dark/circle-accent.png
dfvue/themes/azure-2.0/theme/dark/circle-basic.png
dfvue/themes/azure-2.0/theme/dark/circle-hover.png
dfvue/themes/azure-2.0/theme/dark/combo-button-basic.png
dfvue/themes/azure-2.0/theme/dark/combo-button-focus.png
dfvue/themes/azure-2.0/theme/dark/combo-button-hover.png
dfvue/themes/azure-2.0/theme/dark/down-accent.png
dfvue/themes/azure-2.0/theme/dark/down.png
dfvue/themes/azure-2.0/theme/dark/empty.png
dfvue/themes/azure-2.0/theme/dark/hor-accent.png
dfvue/themes/azure-2.0/theme/dark/hor-basic.png
dfvue/themes/azure-2.0/theme/dark/hor-hover.png
dfvue/themes/azure-2.0/theme/dark/notebook.png
dfvue/themes/azure-2.0/theme/dark/off-basic.png
dfvue-6.5.1.dist-info/licenses/AUTHORS.rst
dfvue-6.5.1.dist-info/licenses/LICENSE
dfvue-6.5.1.dist-info/METADATA
dfvue-6.5.1.dist-info/WHEEL
dfvue-6.5.1.dist-info/entry_points.txt
dfvue-6.5.1.dist-info/top_level.txt
dfvue-6.5.1.dist-info/RECORD
