Metadata-Version: 2.4
Name: dfvue
Version: 6.5.1
Summary: dfvue: A minimal GUI for a quick view of csv files
Home-page: https://github.com/mcuntz/dfvue
Author: Matthias Cuntz
Author-email: mc@macu.de
Maintainer: Matthias Cuntz
Maintainer-email: mc@macu.de
License: MIT
Project-URL: Documentation, https://mcuntz.github.io/dfvue/
Project-URL: Source, https://github.com/mcuntz/dfvue
Project-URL: Tracker, https://github.com/mcuntz/dfvue/issues
Project-URL: Changelog, https://github.com/mcuntz/dfvue/blob/main/CHANGELOG.rst
Project-URL: Conda-Forge, https://anaconda.org/conda-forge/dfvue
Platform: any
Classifier: Development Status :: 5 - Production/Stable
Classifier: Intended Audience :: Developers
Classifier: Intended Audience :: End Users/Desktop
Classifier: Intended Audience :: Science/Research
Classifier: Natural Language :: English
Classifier: Operating System :: MacOS
Classifier: Operating System :: MacOS :: MacOS X
Classifier: Operating System :: Microsoft
Classifier: Operating System :: Microsoft :: Windows
Classifier: Operating System :: POSIX
Classifier: Operating System :: Unix
Classifier: Programming Language :: Python
Classifier: Programming Language :: Python :: 3
Classifier: Programming Language :: Python :: 3 :: Only
Classifier: Programming Language :: Python :: 3.8
Classifier: Programming Language :: Python :: 3.9
Classifier: Programming Language :: Python :: 3.10
Classifier: Programming Language :: Python :: 3.11
Classifier: Programming Language :: Python :: 3.12
Classifier: Programming Language :: Python :: 3.13
Classifier: Topic :: Scientific/Engineering
Classifier: Topic :: Scientific/Engineering :: Atmospheric Science
Classifier: Topic :: Scientific/Engineering :: Hydrology
Classifier: Topic :: Scientific/Engineering :: Mathematics
Classifier: Topic :: Software Development
Classifier: Topic :: Utilities
Requires-Python: >=3.8
License-File: LICENSE
License-File: AUTHORS.rst
Requires-Dist: numpy
Requires-Dist: matplotlib
Requires-Dist: pandas
Provides-Extra: doc
Requires-Dist: numpydoc<2,>=1.1; extra == "doc"
Requires-Dist: sphinx<4,>=3; extra == "doc"
Requires-Dist: sphinx_book_theme>=1.0.1; extra == "doc"
Provides-Extra: test
Requires-Dist: coverage[toml]<6,>=5.2.1; extra == "test"
Requires-Dist: pytest<7,>=6.0; extra == "test"
Requires-Dist: pytest-cov<3,>=2.11.0; extra == "test"
Dynamic: license-file
